{
  "hash": "1037f320",
  "configHash": "138e2f1b",
  "lockfileHash": "b3914fb6",
  "browserHash": "7e6ff361",
  "optimized": {
    "react": {
      "src": "../../node_modules/react/index.js",
      "file": "react.js",
      "fileHash": "405e2f87",
      "needsInterop": true
    },
    "react-dom/client": {
      "src": "../../node_modules/react-dom/client.js",
      "file": "react-dom_client.js",
      "fileHash": "812b0e78",
      "needsInterop": true
    },
    "react-router-dom": {
      "src": "../../node_modules/react-router-dom/dist/index.js",
      "file": "react-router-dom.js",
      "fileHash": "d0e47c76",
      "needsInterop": false
    },
    "react-big-calendar": {
      "src": "../../node_modules/react-big-calendar/dist/react-big-calendar.esm.js",
      "file": "react-big-calendar.js",
      "fileHash": "382caeee",
      "needsInterop": false
    },
    "gapi-script": {
      "src": "../../node_modules/gapi-script/index.js",
      "file": "gapi-script.js",
      "fileHash": "56f56c93",
      "needsInterop": false
    },
    "moment": {
      "src": "../../node_modules/moment/dist/moment.js",
      "file": "moment.js",
      "fileHash": "b3c24120",
      "needsInterop": false
    }
  },
  "chunks": {
    "chunk-ZU5SFTFX": {
      "file": "chunk-ZU5SFTFX.js"
    },
    "chunk-QTVD6AVW": {
      "file": "chunk-QTVD6AVW.js"
    },
    "chunk-PR4QN5HX": {
      "file": "chunk-PR4QN5HX.js"
    }
  }
}